ss_package/__init__.py
ss_package/operations.py
package_dev-0.1.0.dist-info/LICENSE
package_dev-0.1.0.dist-info/METADATA
package_dev-0.1.0.dist-info/WHEEL
package_dev-0.1.0.dist-info/top_level.txt
package_dev-0.1.0.dist-info/RECORD
