Metadata-Version: 2.1
Name: package-dev
Version: 0.1.0
Summary: A simple package with basic functions
Home-page: https://github.com/sravanthi69/package-dev
Author: sravs
Author-email: sravanthi23.2001@gmail.com
Classifier: Programming Language :: Python :: 3
Classifier: License :: OSI Approved :: MIT License
Classifier: Operating System :: OS Independent
Requires-Python: >=3.6
License-File: LICENSE
